MANIFEST.in
__info__.py
setup.py
./appomatic_cmsplugin_phlog.egg-info/SOURCES.txt
./appomatic_cmsplugin_phlog.egg-info/dependency_links.txt
./appomatic_cmsplugin_phlog.egg-info/requires.txt
./appomatic_cmsplugin_phlog.egg-info/top_level.txt
appomatic_cmsplugin_phlog/__app__.py
appomatic_cmsplugin_phlog/__init__.py
appomatic_cmsplugin_phlog.egg-info/PKG-INFO
appomatic_cmsplugin_phlog.egg-info/SOURCES.txt
appomatic_cmsplugin_phlog.egg-info/dependency_links.txt
appomatic_cmsplugin_phlog.egg-info/requires.txt
appomatic_cmsplugin_phlog.egg-info/top_level.txt