Metadata-Version: 1.0
Name: appomatic-cmsplugin-phlog
Version: 0.0.31
Summary: Integrates django-cms and Photologue
Home-page: https://github.com/benliles/cmsplugin-phlog
Author: RedHog (Egil Moeller)
Author-email: egil.moller@freecode.no
License: GPL
Keywords: appomatic django-cms photologue
Platform: UNKNOWN
